{
  "date": "2025-10-09",
  "projects": {
    "Untitled (Workspace)": {
      "totalLinesAdded": 338,
      "totalLinesRemoved": 0,
      "totalActiveTime": 10,
      "files": {
        "e:\\Siti\\Kinsta\\naturalnicheperfume premium\\wp-content\\plugins\\jmb-woocommerce-recaptcha\\jmb-woocommerce-recaptcha.php": [
          {
            "timestamp": "2025-10-09T08:56:21.678Z",
            "fileName": "e:\\Siti\\Kinsta\\naturalnicheperfume premium\\wp-content\\plugins\\jmb-woocommerce-recaptcha\\jmb-woocommerce-recaptcha.php",
            "fileType": ".php",
            "linesAdded": 243,
            "linesRemoved": 0,
            "projectName": "Untitled (Workspace)",
            "content": {
              "added": [],
              "removed": []
            },
            "duration": 0,
            "language": "php"
          },
          {
            "timestamp": "2025-10-09T09:02:22.437Z",
            "fileName": "e:\\Siti\\Kinsta\\naturalnicheperfume premium\\wp-content\\plugins\\jmb-woocommerce-recaptcha\\jmb-woocommerce-recaptcha.php",
            "fileType": ".php",
            "linesAdded": 27,
            "linesRemoved": 0,
            "projectName": "Untitled (Workspace)",
            "content": {
              "added": [],
              "removed": []
            },
            "duration": 0,
            "language": "php"
          },
          {
            "timestamp": "2025-10-09T09:05:53.086Z",
            "fileName": "e:\\Siti\\Kinsta\\naturalnicheperfume premium\\wp-content\\plugins\\jmb-woocommerce-recaptcha\\jmb-woocommerce-recaptcha.php",
            "fileType": ".php",
            "linesAdded": 13,
            "linesRemoved": 0,
            "projectName": "Untitled (Workspace)",
            "content": {
              "added": [],
              "removed": []
            },
            "duration": 4,
            "language": "php"
          },
          {
            "timestamp": "2025-10-09T09:08:39.802Z",
            "fileName": "e:\\Siti\\Kinsta\\naturalnicheperfume premium\\wp-content\\plugins\\jmb-woocommerce-recaptcha\\jmb-woocommerce-recaptcha.php",
            "fileType": ".php",
            "linesAdded": 38,
            "linesRemoved": 0,
            "projectName": "Untitled (Workspace)",
            "content": {
              "added": [],
              "removed": []
            },
            "duration": 3,
            "language": "php"
          },
          {
            "timestamp": "2025-10-09T09:10:48.703Z",
            "fileName": "e:\\Siti\\Kinsta\\naturalnicheperfume premium\\wp-content\\plugins\\jmb-woocommerce-recaptcha\\jmb-woocommerce-recaptcha.php",
            "fileType": ".php",
            "linesAdded": 17,
            "linesRemoved": 0,
            "projectName": "Untitled (Workspace)",
            "content": {
              "added": [],
              "removed": []
            },
            "duration": 3,
            "language": "php"
          }
        ]
      },
      "languageStats": {
        "php": 0
      },
      "changeFrequency": {
        "10": 0
      },
      "topFiles": [
        "e:\\Siti\\Kinsta\\naturalnicheperfume premium\\wp-content\\plugins\\jmb-woocommerce-recaptcha\\jmb-woocommerce-recaptcha.php"
      ],
      "averageChangeSize": 243
    }
  },
  "totalActiveTime": 0,
  "totalProjects": 1,
  "totalFiles": 1,
  "mostActiveHours": [
    10
  ],
  "mostUsedLanguages": [
    "php"
  ]
}